CHANGES.txt
LICENSE.txt
MANIFEST.in
README.md
setup.py
cartridge_tax/__init__.py
cartridge_tax/admin.py
cartridge_tax/checkout.py
cartridge_tax/defaults.py
cartridge_tax/forms.py
cartridge_tax/models.py
cartridge_tax/tests.py
cartridge_tax/utils.py
cartridge_tax.egg-info/PKG-INFO
cartridge_tax.egg-info/SOURCES.txt
cartridge_tax.egg-info/dependency_links.txt
cartridge_tax.egg-info/not-zip-safe
cartridge_tax.egg-info/requires.txt
cartridge_tax.egg-info/top_level.txt
cartridge_tax/static/js/taxcloud-tic.js
cartridge_tax/templates/shop/checkout.html
cartridge_tax/templates/shop/includes/order_details.html
cartridge_tax/templates/shop/includes/order_totals.html
cartridge_tax/templates/shop/includes/order_totals.txt
cartridge_tax/templatetags/__init__.py
cartridge_tax/templatetags/tax_tags.py