Metadata-Version: 1.0
Name: cartridge-tax
Version: 0.0.3
Summary: A tax module for Cartridge.
Home-page: http://pypi.python.org/pypi/cartridge-tax/
Author: Kenneth Bolton
Author-email: kenbolton@gmail.com
License: LICENSE.txt
Platform: UNKNOWN
